rest_framework_tricks/__init__.py
rest_framework_tricks/apps.py
rest_framework_tricks/helpers.py
rest_framework_tricks/utils.py
rest_framework_tricks/fields/__init__.py
rest_framework_tricks/fields/file.py
rest_framework_tricks/filters/__init__.py
rest_framework_tricks/filters/ordering.py
rest_framework_tricks/models/__init__.py
rest_framework_tricks/models/fields/__init__.py
rest_framework_tricks/models/fields/nested_proxy.py
rest_framework_tricks/serializers/__init__.py
rest_framework_tricks/serializers/nested_proxy.py
rest_framework_tricks/tests/__init__.py
rest_framework_tricks/tests/base.py
rest_framework_tricks/tests/test_fields.py
rest_framework_tricks/tests/test_nested_proxy_field.py
rest_framework_tricks/tests/test_ordering_filter.py
rest_framework_tricks/tests/test_utils.py
django_rest_framework_tricks-0.2.14.dist-info/LICENSE_GPL2.0.txt
django_rest_framework_tricks-0.2.14.dist-info/LICENSE_LGPL_2.1.txt
django_rest_framework_tricks-0.2.14.dist-info/METADATA
django_rest_framework_tricks-0.2.14.dist-info/WHEEL
django_rest_framework_tricks-0.2.14.dist-info/top_level.txt
django_rest_framework_tricks-0.2.14.dist-info/RECORD
