Metadata-Version: 2.1
Name: django-rest-framework-tricks
Version: 0.2.14
Summary: Collection of various tricks for Django REST framework.
Home-page: https://github.com/barseghyanartur/django-rest-framework-tricks/
Author: Artur Barseghyan
Author-email: artur.barseghyan@gmail.com
License: GPL-2.0-only OR LGPL-2.1-or-later
Project-URL: Bug Tracker, https://github.com/barseghyanartur/django-rest-framework-tricks/
Project-URL: Documentation, https://django-rest-framework-tricks.readthedocs.io/
Project-URL: Source Code, https://github.com/barseghyanartur/django-rest-framework-tricks/
Project-URL: Changelog, https://django-rest-framework-tricks.readthedocs.io/en/latest/changelog.html
Keywords: django,django rest framework,tricks
Classifier: Programming Language :: Python :: 3.7
Classifier: Programming Language :: Python :: 3.8
Classifier: Programming Language :: Python :: 3.9
Classifier: Programming Language :: Python :: 3.10
Classifier: Programming Language :: Python :: 3.11
Classifier: Environment :: Web Environment
Classifier: License :: OSI Approved :: GNU General Public License v2 (GPLv2)
Classifier: License :: OSI Approved :: GNU Lesser General Public License v2 or later (LGPLv2+)
Classifier: Framework :: Django
Classifier: Framework :: Django :: 2.2
Classifier: Framework :: Django :: 3.0
Classifier: Framework :: Django :: 3.1
Classifier: Framework :: Django :: 3.2
Classifier: Framework :: Django :: 4.0
Classifier: Framework :: Django :: 4.1
Classifier: Intended Audience :: Developers
Classifier: Operating System :: OS Independent
Classifier: Development Status :: 4 - Beta
License-File: LICENSE_GPL2.0.txt
License-File: LICENSE_LGPL_2.1.txt
Requires-Dist: djangorestframework
Requires-Dist: humanize
